LinkedList.py
Stack.py
helpdesk.py
ticket.py
interactive_helpdesk_cli-0.1.0.dist-info/METADATA
interactive_helpdesk_cli-0.1.0.dist-info/WHEEL
interactive_helpdesk_cli-0.1.0.dist-info/entry_points.txt
interactive_helpdesk_cli-0.1.0.dist-info/top_level.txt
interactive_helpdesk_cli-0.1.0.dist-info/RECORD
