Metadata-Version: 2.4
Name: interactive-helpdesk-cli
Version: 0.1.0
Summary: Interactive Help Desk ticket system CLI using data structures
Home-page: https://github.com/Prashidha0O1/helpdesk_cli
Author: Prashidha
License: MIT
Project-URL: Source, https://github.com/Prashidha0O1/helpdesk_cli
Project-URL: Issues, https://github.com/Prashidha0O1/helpdesk_cli/issues
Classifier: Programming Language :: Python :: 3
Classifier: License :: OSI Approved :: MIT License
Classifier: Operating System :: OS Independent
Classifier: Environment :: Console
Classifier: Topic :: Utilities
Requires-Python: >=3.9
Requires-Dist: click<9.0,>=8.0
Dynamic: author
Dynamic: classifier
Dynamic: description
Dynamic: description-content-type
Dynamic: home-page
Dynamic: license
Dynamic: project-url
Dynamic: requires-dist
Dynamic: requires-python
Dynamic: summary
